tqdm_tag/__init__.py
tqdm_tag/tqdm_tag.py
tqdm_tag-0.2.8.dist-info/METADATA
tqdm_tag-0.2.8.dist-info/WHEEL
tqdm_tag-0.2.8.dist-info/licenses/LICENSE
tqdm_tag-0.2.8.dist-info/RECORD
