Metadata-Version: 2.4
Name: tqdm-tag
Version: 0.2.8
Summary: Enhance tqdm progress bars by assigning tags and colors to iterations.
Project-URL: Documentation, https://github.com/Colin Moldenhauer/tqdm-tag#readme
Project-URL: Issues, https://github.com/Colin Moldenhauer/tqdm-tag/issues
Project-URL: Source, https://github.com/Colin Moldenhauer/tqdm-tag
Author-email: Colin Moldenhauer <colin.moldenhauer@posteo.de>
License-Expression: MIT
License-File: LICENSE
Classifier: Development Status :: 4 - Beta
Classifier: Programming Language :: Python
Classifier: Programming Language :: Python :: 3.8
Classifier: Programming Language :: Python :: 3.9
Classifier: Programming Language :: Python :: 3.10
Classifier: Programming Language :: Python :: 3.11
Classifier: Programming Language :: Python :: 3.12
Classifier: Programming Language :: Python :: Implementation :: CPython
Classifier: Programming Language :: Python :: Implementation :: PyPy
Requires-Python: >=3.8
Requires-Dist: numpy
Requires-Dist: tqdm
